Classfile /home/ciro/bak/git/java-cheat/javac/generated-bytecode/CompileTimeConstant.class
  Last modified Apr 3, 2015; size 525 bytes
  MD5 checksum ec3d358acb98c827a644c7f43485c157
  Compiled from "CompileTimeConstant.java"
public class CompileTimeConstant
  SourceFile: "CompileTimeConstant.java"
  minor version: 0
  major version: 51
  flags: ACC_PUBLIC, ACC_SUPER
Constant pool:
   #1 = Methodref          #5.#19         //  java/lang/Object."<init>":()V
   #2 = Fieldref           #20.#21        //  java/lang/System.out:Ljava/io/PrintStream;
   #3 = Methodref          #22.#23        //  java/io/PrintStream.println:(I)V
   #4 = Class              #24            //  CompileTimeConstant
   #5 = Class              #25            //  java/lang/Object
   #6 = Utf8               <init>
   #7 = Utf8               ()V
   #8 = Utf8               Code
   #9 = Utf8               LineNumberTable
  #10 = Utf8               LocalVariableTable
  #11 = Utf8               this
  #12 = Utf8               LCompileTimeConstant;
  #13 = Utf8               main
  #14 = Utf8               ([Ljava/lang/String;)V
  #15 = Utf8               args
  #16 = Utf8               [Ljava/lang/String;
  #17 = Utf8               SourceFile
  #18 = Utf8               CompileTimeConstant.java
  #19 = NameAndType        #6:#7          //  "<init>":()V
  #20 = Class              #26            //  java/lang/System
  #21 = NameAndType        #27:#28        //  out:Ljava/io/PrintStream;
  #22 = Class              #29            //  java/io/PrintStream
  #23 = NameAndType        #30:#31        //  println:(I)V
  #24 = Utf8               CompileTimeConstant
  #25 = Utf8               java/lang/Object
  #26 = Utf8               java/lang/System
  #27 = Utf8               out
  #28 = Utf8               Ljava/io/PrintStream;
  #29 = Utf8               java/io/PrintStream
  #30 = Utf8               println
  #31 = Utf8               (I)V
{
  public CompileTimeConstant();
    flags: ACC_PUBLIC
    Code:
      stack=1, locals=1, args_size=1
         0: aload_0       
         1: invokespecial #1                  // Method java/lang/Object."<init>":()V
         4: return        
      LineNumberTable:
        line 1: 0
      LocalVariableTable:
        Start  Length  Slot  Name   Signature
               0       5     0  this   LCompileTimeConstant;

  public static void main(java.lang.String[]);
    flags: ACC_PUBLIC, ACC_STATIC
    Code:
      stack=2, locals=1, args_size=1
         0: getstatic     #2                  // Field java/lang/System.out:Ljava/io/PrintStream;
         3: iconst_2      
         4: invokevirtual #3                  // Method java/io/PrintStream.println:(I)V
         7: return        
      LineNumberTable:
        line 5: 0
        line 6: 7
      LocalVariableTable:
        Start  Length  Slot  Name   Signature
               0       8     0  args   [Ljava/lang/String;
}
